brick3/__init__.py
brick3/config.py
brick3/gateway.py
brick3/mempool.py
brick3/setup.py
brick3/setup_integration.py
brick3/transaction.py
brick3/utils.py
brick3/virtuals_integration.py
brick3/examples/mev_calculator_example.py
brick3/examples/trading_bot_example.py
brick3/examples/virtuals_agent_example.py
brick3-1.0.0.dist-info/licenses/LICENSE
brick3-1.0.0.dist-info/METADATA
brick3-1.0.0.dist-info/WHEEL
brick3-1.0.0.dist-info/top_level.txt
brick3-1.0.0.dist-info/RECORD
