Metadata-Version: 2.4
Name: brick3
Version: 1.0.0
Summary: Ultra-fast MEV infrastructure for AI agents on Monad
Author-email: Brick3 Team <team@brick3.io>
License: MIT
Project-URL: Homepage, https://github.com/brienteth/brick3
Project-URL: Documentation, https://github.com/brienteth/brick3#documentation
Project-URL: Repository, https://github.com/brienteth/brick3.git
Project-URL: Issues, https://github.com/brienteth/brick3/issues
Keywords: mev,blockchain,monad,ai-agents,virtuals,fastlane,arbitrage,trading
Classifier: Development Status :: 4 - Beta
Classifier: Intended Audience :: Developers
Classifier: License :: OSI Approved :: MIT License
Classifier: Programming Language :: Python :: 3
Classifier: Programming Language :: Python :: 3.8
Classifier: Programming Language :: Python :: 3.9
Classifier: Programming Language :: Python :: 3.10
Classifier: Programming Language :: Python :: 3.11
Classifier: Programming Language :: Python :: 3.12
Classifier: Topic :: Software Development :: Libraries :: Python Modules
Classifier: Topic :: Office/Business :: Financial :: Point-Of-Sale
Requires-Python: >=3.8
License-File: LICENSE
Requires-Dist: aiohttp>=3.8.0
Requires-Dist: web3>=6.0.0
Requires-Dist: eth-keys>=0.4.0
Requires-Dist: eth-account>=0.9.0
Provides-Extra: dev
Requires-Dist: pytest>=7.0.0; extra == "dev"
Requires-Dist: pytest-asyncio>=0.21.0; extra == "dev"
Requires-Dist: black>=23.0.0; extra == "dev"
Requires-Dist: flake8>=6.0.0; extra == "dev"
Requires-Dist: mypy>=1.0.0; extra == "dev"
Provides-Extra: virtuals
Requires-Dist: virtuals>=1.0.0; extra == "virtuals"
Dynamic: license-file
